bibfish/__init__.py
bibfish/_version.py
bibfish-0.3.3.dist-info/LICENSE.md
bibfish-0.3.3.dist-info/METADATA
bibfish-0.3.3.dist-info/WHEEL
bibfish-0.3.3.dist-info/entry_points.txt
bibfish-0.3.3.dist-info/top_level.txt
bibfish-0.3.3.dist-info/RECORD
