Metadata-Version: 2.1
Name: bibfish
Version: 0.3.3
Summary: Extract entries from a .bib file that are cited in a .tex file
Author-email: Jon Carr <jon.carr@rhul.ac.uk>
License: MIT
Project-URL: Homepage, https://github.com/jwcarr/bibfish
Classifier: Programming Language :: Python :: 3
Classifier: License :: OSI Approved :: MIT License
Classifier: Operating System :: OS Independent
Classifier: Development Status :: 4 - Beta
Classifier: Intended Audience :: Science/Research
Classifier: Topic :: Text Processing :: Markup :: LaTeX
Requires-Python: >=3.6
License-File: LICENSE.md
Requires-Dist: bibtexparser ==1.4.1
